sudulunu/__init__.py
sudulunu/helpers.py
sudulunu/matchers.py
sudulunu-0.1.1.dist-info/LICENSE
sudulunu-0.1.1.dist-info/METADATA
sudulunu-0.1.1.dist-info/WHEEL
sudulunu-0.1.1.dist-info/top_level.txt
sudulunu-0.1.1.dist-info/RECORD
